rabbitmq_easy/__init__.py
rabbitmq_easy/decorators.py
rabbitmq_easy/exceptions.py
rabbitmq_easy/manager.py
rabbitmq_easy/utils.py
rabbitmq_easy-1.0.5.dist-info/licenses/LICENSE
tests/__init__.py
tests/test_manager.py
rabbitmq_easy-1.0.5.dist-info/METADATA
rabbitmq_easy-1.0.5.dist-info/WHEEL
rabbitmq_easy-1.0.5.dist-info/top_level.txt
rabbitmq_easy-1.0.5.dist-info/RECORD
