Metadata-Version: 2.4
Name: rabbitmq-easy
Version: 1.0.5
Summary: A simple, robust RabbitMQ manager for Python applications
Home-page: https://github.com/mount-isaac/rabbitmq-easy
Author: Isaac Kyalo
Author-email: Isaac Kyalo <isadechair019@gmail.com>
License: MIT
Project-URL: Homepage, https://github.com/mount-isaac/rabbitmq-easy
Project-URL: Bug Reports, https://github.com/mount-isaac/rabbitmq-easy/issues
Project-URL: Source, https://github.com/mount-isaac/rabbitmq-easy
Classifier: Development Status :: 5 - Production/Stable
Classifier: Intended Audience :: Developers
Classifier: License :: OSI Approved :: MIT License
Classifier: Operating System :: OS Independent
Classifier: Programming Language :: Python :: 3
Classifier: Programming Language :: Python :: 3.7
Classifier: Programming Language :: Python :: 3.8
Classifier: Programming Language :: Python :: 3.9
Classifier: Programming Language :: Python :: 3.10
Classifier: Programming Language :: Python :: 3.11
Classifier: Programming Language :: Python :: 3.12
Classifier: Programming Language :: Python :: 3.13
Requires-Python: >=3.7
License-File: LICENSE
Requires-Dist: pika>=1.2.0
Requires-Dist: python-dotenv>=0.19.0
Provides-Extra: dev
Requires-Dist: pytest>=6.0; extra == "dev"
Requires-Dist: pytest-cov; extra == "dev"
Requires-Dist: black; extra == "dev"
Requires-Dist: flake8; extra == "dev"
Requires-Dist: mypy; extra == "dev"
Requires-Dist: twine; extra == "dev"
Requires-Dist: wheel; extra == "dev"
Dynamic: author
Dynamic: home-page
Dynamic: license-file
Dynamic: requires-python
